defix_package_queues/__init__.py
defix_package_queues/constants.py
defix_package_queues/utils.py
defix_package_queues/helpers/__init__.py
defix_package_queues/helpers/consumer.py
defix_package_queues/helpers/sqs_api.py
defix_package_queues/queues/__init__.py
defix_package_queues/queues/basic.py
defix_package_queues-0.1.7.dist-info/METADATA
defix_package_queues-0.1.7.dist-info/WHEEL
defix_package_queues-0.1.7.dist-info/entry_points.txt
defix_package_queues-0.1.7.dist-info/RECORD
