Metadata-Version: 2.4
Name: defix-package-queues
Version: 0.1.7
Summary: DeFiX internal package for working with AWS SQS
Author-email: Mykhailo Kuzmin <guywithnothing56@gmail.com>
Requires-Python: >=3.9
Requires-Dist: aws-sqs-consumer>=0.0.15
Requires-Dist: boto3>=1.37.19
Requires-Dist: defix-package-logger>=0.1.2
Requires-Dist: python-dateutil>=2.9.0.post0
